cloudimg/__init__.py
cloudimg/aws.py
cloudimg/common.py
cloudimg/ms_azure.py
cloudimg-1.15.0.dist-info/LICENSE
cloudimg-1.15.0.dist-info/METADATA
cloudimg-1.15.0.dist-info/WHEEL
cloudimg-1.15.0.dist-info/top_level.txt
cloudimg-1.15.0.dist-info/RECORD
