Metadata-Version: 2.1
Name: cloudimg
Version: 1.15.0
Summary: Services for building and releasing products in cloud environments
Home-page: https://github.com/release-engineering/cloudimg
Author: Alex Misstear
Author-email: amisstea@redhat.com
License: GPLv3
Platform: UNKNOWN
Classifier: Intended Audience :: Developers
Classifier: License :: OSI Approved :: GNU Lesser General Public License v3 (LGPLv3)
Classifier: Programming Language :: Python
Classifier: Programming Language :: Python :: 3
Classifier: Programming Language :: Python :: 3.6
Classifier: Programming Language :: Python :: 3.7
Classifier: Programming Language :: Python :: 3.8
Requires-Python: >=3.6
Requires-Dist: azure-storage-blob
Requires-Dist: azure-mgmt-storage
Requires-Dist: attrs
Requires-Dist: boto3
Requires-Dist: requests
Requires-Dist: tenacity
Requires-Dist: monotonic; python_version < "3.3"
